tale/__init__.py
tale/filters.py
tale/plugins.py
tale/utils.py
tale/templates/404.html
tale/templates/__init__.py
tale/templates/_footer.html
tale/templates/_header.html
tale/templates/base.html
tale/templates/list.html
tale/templates/main.html
tale/templates/mkdocs_theme.yml
tale/templates/assets/styles/main.css
tale/templates/macros/toc.html
mkdocs_tale-0.1.7.dist-info/METADATA
mkdocs_tale-0.1.7.dist-info/WHEEL
mkdocs_tale-0.1.7.dist-info/entry_points.txt
mkdocs_tale-0.1.7.dist-info/top_level.txt
mkdocs_tale-0.1.7.dist-info/RECORD
