Metadata-Version: 2.4
Name: mkdocs-tale
Version: 0.1.7
Summary: A simple theme of mkdocs
Author-email: Your Name <your@email.com>
License: MIT
Project-URL: Source, https://github.com/RyanPoy/mkdocs-tale
Project-URL: Issues, https://github.com/RyanPoy/mkdocs-tale/issues
Keywords: mkdocs,plugin,theme
Requires-Python: >=3.13
Requires-Dist: build>=1.2.2.post1
Requires-Dist: mkdocs>=1.6.1
